CHANGES.rst
MANIFEST.in
README.rst
setup.cfg
setup.py
pywebuml/__init__.py
pywebuml/app.py
pywebuml/commands.py
pywebuml/filters.py
pywebuml/models.py
pywebuml/package_tree.py
pywebuml/settings.py
pywebuml/web.py
pywebuml.egg-info/PKG-INFO
pywebuml.egg-info/SOURCES.txt
pywebuml.egg-info/dependency_links.txt
pywebuml.egg-info/entry_points.txt
pywebuml.egg-info/not-zip-safe
pywebuml.egg-info/requires.txt
pywebuml.egg-info/top_level.txt
pywebuml/parsers/__init__.py
pywebuml/parsers/base.py
pywebuml/parsers/constants.py
pywebuml/parsers/exceptions.py
pywebuml/parsers/main.py
pywebuml/parsers/parser_factory.py
pywebuml/parsers/python.py
pywebuml/parsers/utils.py
pywebuml/parsers/csharp/__init__.py
pywebuml/parsers/csharp/attribute_parser.py
pywebuml/parsers/csharp/class_parser.py
pywebuml/parsers/csharp/file_parser.py
pywebuml/parsers/csharp/method_parser.py
pywebuml/parsers/csharp/package_manager.py
pywebuml/parsers/java/__init__.py
pywebuml/parsers/java/attribute_parser.py
pywebuml/parsers/java/class_parser.py
pywebuml/parsers/java/file_parser.py
pywebuml/parsers/java/method_parser.py
pywebuml/parsers/java/package_manager.py
pywebuml/parsers/static_typed/__init__.py
pywebuml/parsers/static_typed/attribute_parser.py
pywebuml/parsers/static_typed/class_parser.py
pywebuml/parsers/static_typed/file_parser.py
pywebuml/parsers/static_typed/method_parser.py
pywebuml/parsers/static_typed/package_manager.py
pywebuml/static/css/jquery.treeview.css
pywebuml/static/css/pywebuml.css
pywebuml/static/css/reset.css
pywebuml/static/css/smoothness/jquery-ui-1.8.9.custom.css
pywebuml/static/css/smoothness/images/ui-bg_flat_0_aaaaaa_40x100.png
pywebuml/static/css/smoothness/images/ui-bg_flat_75_ffffff_40x100.png
pywebuml/static/css/smoothness/images/ui-bg_glass_55_fbf9ee_1x400.png
pywebuml/static/css/smoothness/images/ui-bg_glass_65_ffffff_1x400.png
pywebuml/static/css/smoothness/images/ui-bg_glass_75_dadada_1x400.png
pywebuml/static/css/smoothness/images/ui-bg_glass_75_e6e6e6_1x400.png
pywebuml/static/css/smoothness/images/ui-bg_glass_95_fef1ec_1x400.png
pywebuml/static/css/smoothness/images/ui-bg_highlight-soft_75_cccccc_1x100.png
pywebuml/static/css/smoothness/images/ui-icons_222222_256x240.png
