Metadata-Version: 1.0
Name: pywebuml
Version: 0.3.0
Summary: Creates UML diagrams from code
Home-page: http://bitbucket.org/tzulberti/pywebuml
Author: Tomas Zulberti
Author-email: tzulberti@gmail.com
License: BSD
Keywords: uml
Platform: UNKNOWN
Classifier: Development Status :: 4 - Beta
Classifier: Programming Language :: Java
Classifier: Programming Language :: C#
Classifier: Topic :: Documentation
Classifier: Topic :: Software Development :: Documentation
Classifier: Intended Audience :: Developers
Classifier: License :: OSI Approved :: BSD License
Classifier: Operating System :: OS Independent
Classifier: Programming Language :: Python :: 2.6
Classifier: Programming Language :: Python :: 2.7
